.DS_Store
visbeat/ADefines.py
visbeat/AFileManager.py
visbeat/AFuncDict.py
visbeat/AImports.py
visbeat/AObject.py
visbeat/AParamDict.py
visbeat/Audio.py
visbeat/AudioClip.py
visbeat/Event.py
visbeat/EventList.py
visbeat/Image.py
visbeat/Image_CV.py
visbeat/SourceLocationParser.py
visbeat/TimeSignal.py
visbeat/TimeSignal1D.py
visbeat/VBMIDI.py
visbeat/VBObject.py
visbeat/Video.py
visbeat/VideoClip.py
visbeat/VideoSource.py
visbeat/Video_CV.py
visbeat/VisBeatDefines.py
visbeat/VisBeatExampleVideo.py
visbeat/VisBeatImports.py
visbeat/VisualBeat.py
visbeat/Warp.py
visbeat/__init__.py
visbeat/_dancefer_examples.py
visbeat/_dancify_examples.py
visbeat/_mediafiles.py
visbeat/_music_examples.py
visbeat/command_line.py
visbeat/_assets/.DS_Store
visbeat/_assets/audio/hit.wav
visbeat/_assets/images/VisBeatWatermark.png
visbeat/fileui/__init__.py
visbeat/fileui/uipath.py
visbeat/vbgui/BeatGUI.py
visbeat/vbgui/__init__.py
visbeat-0.0.9.data/scripts/dancefer
visbeat-0.0.9.dist-info/LICENSE
visbeat-0.0.9.dist-info/METADATA
visbeat-0.0.9.dist-info/WHEEL
visbeat-0.0.9.dist-info/top_level.txt
visbeat-0.0.9.dist-info/RECORD
